conjur_api/__init__.py
conjur_api/client.py
conjur_api/errors/__init__.py
conjur_api/errors/errors.py
conjur_api/errors/ssl_errors.py
conjur_api/http/__init__.py
conjur_api/http/api.py
conjur_api/http/endpoints.py
conjur_api/http/ssl/__init__.py
conjur_api/http/ssl/ssl_consts.py
conjur_api/http/ssl/ssl_context_factory.py
conjur_api/interface/__init__.py
conjur_api/interface/authentication_strategy_interface.py
conjur_api/interface/credentials_store_interface.py
conjur_api/models/__init__.py
conjur_api/models/enums/__init__.py
conjur_api/models/enums/os_types.py
conjur_api/models/general/__init__.py
conjur_api/models/general/conjur_connection_info.py
conjur_api/models/general/credentials_data.py
conjur_api/models/general/proxy_params.py
conjur_api/models/general/resource.py
conjur_api/models/hostfactory/__init__.py
conjur_api/models/hostfactory/create_host_data.py
conjur_api/models/hostfactory/create_token_data.py
conjur_api/models/list/__init__.py
conjur_api/models/list/list_data.py
conjur_api/models/list/list_members_of_data.py
conjur_api/models/list/list_permitted_roles_data.py
conjur_api/models/ssl/__init__.py
conjur_api/models/ssl/ssl_verification_metadata.py
conjur_api/models/ssl/ssl_verification_mode.py
conjur_api/providers/__init__.py
conjur_api/providers/authn_authentication_strategy.py
conjur_api/providers/jwt_authentication_strategy.py
conjur_api/providers/ldap_authentication_strategy.py
conjur_api/providers/oidc_authentication_strategy.py
conjur_api/providers/simple_credentials_provider.py
conjur_api/providers/token_authentication_strategy.py
conjur_api/utils/__init__.py
conjur_api/utils/decorators.py
conjur_api/utils/util_functions.py
conjur_api/wrappers/__init__.py
conjur_api/wrappers/http_response.py
conjur_api/wrappers/http_wrapper.py
conjur_api-0.1.9.dist-info/licenses/LICENSE
conjur_api-0.1.9.dist-info/METADATA
conjur_api-0.1.9.dist-info/WHEEL
conjur_api-0.1.9.dist-info/top_level.txt
conjur_api-0.1.9.dist-info/zip-safe
conjur_api-0.1.9.dist-info/RECORD
