Metadata-Version: 2.4
Name: conjur_api
Version: 0.1.9
Summary: HTTP client for CyberArk Conjur Secrets Manager
Home-page: https://github.com/cyberark/conjur-api-python
License: Apache 2
Project-URL: GitHub: repo, https://github.com/cyberark/conjur-api-python
Classifier: Development Status :: 5 - Production/Stable
Classifier: Intended Audience :: Developers
Classifier: License :: OSI Approved :: Apache Software License
Classifier: Operating System :: POSIX
Classifier: Operating System :: MacOS :: MacOS X
Classifier: Operating System :: Microsoft :: Windows
Classifier: Programming Language :: Python
Classifier: Programming Language :: Python :: 3
Classifier: Programming Language :: Python :: 3.10
Classifier: Topic :: Security
Requires-Python: >=3.10.1
License-File: LICENSE
Requires-Dist: cryptography~=44.0.3
Requires-Dist: keyring>=25.5.0
Requires-Dist: aiohttp>=3.10.10
Requires-Dist: asynctest>=0.13.0; python_version < "3.8"
Requires-Dist: setuptools>=80.0.0
Requires-Dist: urllib3>=2.2.2
Dynamic: license-file
